{
  "kind": "singleType",
  "collectionName": "canal_de_denuncias",
  "info": {
    "singularName": "canal-de-denuncia",
    "pluralName": "canal-de-denuncias",
    "displayName": "Canal de Denúncias"
  },
  "options": {
    "draftAndPublish": true
  },
  "attributes": {
    "media": {
      "allowedTypes": [
        "images"
      ],
      "type": "media",
      "multiple": false,
      "required": true
    },
    "content": {
      "type": "richtext",
      "required": true
    },
    "link": {
      "type": "string",
      "required": true
    }
  }
}
